{
	"intents": [
		{
			"tag": "greeting",
			"patterns": [
				"Здравей", "Здрасти", "здр", "Добро утро", "Добър ден", "Добър вечер", "Какво става", "Как си", "Как я караш", "Здравей, как си", "Привет", "Хей", "Хеййй", "Хело", "Хелло", "как е", "Ко стаа", "Опа", "Охо", "Здр, как си", "Здр, какво става", "ехо", "Ехо", "Приятно ми е!", "Здрасти, аз съм", "Аз се казвам", "Аз съм ", "Казвам си", "Как се казваш", "Кой си ти?", "Да се запознаем", "Познаваме ли се", "Здрасти как се казваш", "Какво е името ти", "Имаш ли си име", "Здравей, име?"
				],
			"response": "greeting"
		},
		{
			"tag": "weather",
			"patterns": [
				"Как е времето", "Как е навън", "Как е времето навън", "Какво показва прогнозата за времето", "Времето добре ли е", "Навън как е", "Топло ли е навън", "Студено ли е навън", "Как е прогнозата", "Дали ще вали днес", "Навън вали ли", "Прогноза?", "Прогноза", "Време", "Време?", "Интересувам се от времето", "Интересува ме прогнозата", "Какво ще кажеш за времето навън", "Сняг?", "Духа ли вятър", "Мога ли да играя голф днес", "Голфче?", "Дали ше става за игра днес", "Дали да играя днес голф", "за голфа как е", "голф", "добре ли е навън", "как е навън", "вънка", "отвън времето как е", "да излизам ли", "искам да играя голф", "искам да знам времето", "искам да знам прогнозата", "искам прогнозата", "помогни за голфа", "помогни с времето", "покажи ми времето", "искам да ми покажеш времето навън", "искам да ми покажеш прогнозата", "трябва да знам за времето", "тук съм за прогнозата", "я покажи прогнозата", "искам прогнозата днес", "тая прогноза ми трябва", "времето днес?", "времето подходящо ли е за игра на голф", "времето става ли за голф", "голф ще се играе ли днес"
				],
			"response": "weather"
		},
		{
			"tag": "goodbye",
			"patterns": [
				"Чао", "Довиждане", "Айде чао", "Ще се видим", "Ще се чуем", "До нови срещи", "Тръгвам си", "Трябва да тръгвам", "Трябва да ходя", "Ще си ходя", "Сбогом", "бб", "изход", "затвори", "изключи", "аре", "айде", "ще се чуваме пак", "затварям", "излизам", "дочуване", "лека", "лека нощ", "Чао! Приятен ден", "Поздрави", "Сайонара", "излизам", "ще изляза", "искам да затворя", "искам да изляза", "чао излизам", "чао затварям", "нямам нужда от теб", "не ми пиши повече", "затвори се", "изключи чата", "приключи чата", "затвори чата", "излез от разговора", "излез от чата", "прекрати", "край", "край на разговора", "край на чата"
				],
			"response": "goodbye"
		}
	]
}